LICENSE
MANIFEST.in
README.md
setup.py
GCR/__init__.py
GCR/base.py
GCR/composite.py
GCR/query.py
GCR/utils.py
GCR/version.py
GCR.egg-info/PKG-INFO
GCR.egg-info/SOURCES.txt
GCR.egg-info/dependency_links.txt
GCR.egg-info/requires.txt
GCR.egg-info/top_level.txt