Metadata-Version: 1.2
Name: GCR
Version: 0.9.0
Summary: Generic Catalog Reader: A common reader interface for accessing generic catalogs
Home-page: https://github.com/yymao/generic-catalog-reader
Author: Yao-Yuan Mao
Author-email: yymao.astro@gmail.com
Maintainer: Yao-Yuan Mao
Maintainer-email: yymao.astro@gmail.com
License: MIT
Download-URL: https://github.com/yymao/generic-catalog-reader/archive/v0.9.0.zip
Keywords: GCR catalog reader
Platform: UNKNOWN
Classifier: Intended Audience :: Developers
Classifier: Intended Audience :: Science/Research
Classifier: License :: OSI Approved :: MIT License
Classifier: Programming Language :: Python :: 3.6
